cses/__init__.py
cses/errors.py
cses/structures.py
cses/utils.py
cseslib4py-0.1.3.dist-info/licenses/LICENSE
cseslib4py-0.1.3.dist-info/METADATA
cseslib4py-0.1.3.dist-info/WHEEL
cseslib4py-0.1.3.dist-info/top_level.txt
cseslib4py-0.1.3.dist-info/RECORD
